Metadata-Version: 2.1
Name: abseqPy
Version: 0.99.0
Summary: Quality control pipeline for antibody libraries
Home-page: https://github.com/malhamdoosh/abseqPy
Author: Monther Alhamdoosh
Author-email: m.hamdoosh@gmail.com
Maintainer: Jia Hong Fong
Maintainer-email: jiahfong@gmail.com
License: UNKNOWN
Platform: UNKNOWN
Classifier: Programming Language :: Python :: 2.7
Classifier: License :: OSI Approved :: GNU General Public License v3 (GPLv3)
Classifier: Operating System :: MacOS
Classifier: Operating System :: Microsoft
Classifier: Operating System :: POSIX
Classifier: Operating System :: Unix
Classifier: Topic :: Scientific/Engineering :: Bio-Informatics
Classifier: Intended Audience :: Science/Research
Classifier: Environment :: Console
